{
"counters":{"lamp.*.*.www0....www.denominator":354,"lamp.edda":117,"lamp.us-east-1.*.webserver-elb0....webserver-elb.elb":905,"lamp.us-east-1.zoneA.eureka0....eureka.eureka":148,"lamp.us-east-1.zoneA.memcache0....memcache.store":172,"lamp.us-east-1.zoneA.rds-mysql0....rds-mysql.store":159,"lamp.us-east-1.zoneA.webserver0....webserver.monolith":51,"lamp.us-east-1.zoneA.webserver12....webserver.monolith":64,"lamp.us-east-1.zoneA.webserver15....webserver.monolith":42,"lamp.us-east-1.zoneA.webserver3....webserver.monolith":60,"lamp.us-east-1.zoneA.webserver6....webserver.monolith":61,"lamp.us-east-1.zoneA.webserver9....webserver.monolith":60,"lamp.us-east-1.zoneB.eureka1....eureka.eureka":141,"lamp.us-east-1.zoneB.rds-mysql1....rds-mysql.store":172,"lamp.us-east-1.zoneB.webserver1....webserver.monolith":76,"lamp.us-east-1.zoneB.webserver10....webserver.monolith":45,"lamp.us-east-1.zoneB.webserver13....webserver.monolith":50,"lamp.us-east-1.zoneB.webserver16....webserver.monolith":57,"lamp.us-east-1.zoneB.webserver4....webserver.monolith":47,"lamp.us-east-1.zoneB.webserver7....webserver.monolith":58,"lamp.us-east-1.zoneC.eureka2....eureka.eureka":142,"lamp.us-east-1.zoneC.webserver11....webserver.monolith":58,"lamp.us-east-1.zoneC.webserver14....webserver.monolith":52,"lamp.us-east-1.zoneC.webserver17....webserver.monolith":40,"lamp.us-east-1.zoneC.webserver2....webserver.monolith":51,"lamp.us-east-1.zoneC.webserver5....webserver.monolith":45,"lamp.us-east-1.zoneC.webserver8....webserver.monolith":51}
"gauges":{"lamp.*.*.www0....www.denominator.P50":6143,"lamp.*.*.www0....www.denominator.P75":7167,"lamp.*.*.www0....www.denominator.P90":9727,"lamp.*.*.www0....www.denominator.P95":14847,"lamp.*.*.www0....www.denominator.P99":35839,"lamp.*.*.www0....www.denominator.P999":1097727,"lamp.edda.P50":39935,"lamp.edda.P75":189951,"lamp.edda.P90":389631,"lamp.edda.P95":488447,"lamp.edda.P99":554495,"lamp.edda.P999":658431,"lamp.us-east-1.*.webserver-elb0....webserver-elb.elb.P50":30719,"lamp.us-east-1.*.webserver-elb0....webserver-elb.elb.P75":44543,"lamp.us-east-1.*.webserver-elb0....webserver-elb.elb.P90":68607,"lamp.us-east-1.*.webserver-elb0....webserver-elb.elb.P95":91135,"lamp.us-east-1.*.webserver-elb0....webserver-elb.elb.P99":183295,"lamp.us-east-1.*.webserver-elb0....webserver-elb.elb.P999":1097215,"lamp.us-east-1.zoneA.eureka0....eureka.eureka.P50":12799,"lamp.us-east-1.zoneA.eureka0....eureka.eureka.P75":44031,"lamp.us-east-1.zoneA.eureka0....eureka.eureka.P90":68607,"lamp.us-east-1.zoneA.eureka0....eureka.eureka.P95":109055,"lamp.us-east-1.zoneA.eureka0....eureka.eureka.P99":4706303,"lamp.us-east-1.zoneA.eureka0....eureka.eureka.P999":4710911,"lamp.us-east-1.zoneA.memcache0....memcache.store.P50":8703,"lamp.us-east-1.zoneA.memcache0....memcache.store.P75":11263,"lamp.us-east-1.zoneA.memcache0....memcache.store.P90":13311,"lamp.us-east-1.zoneA.memcache0....memcache.store.P95":15359,"lamp.us-east-1.zoneA.memcache0....memcache.store.P99":38399,"lamp.us-east-1.zoneA.memcache0....memcache.store.P999":1179647,"lamp.us-east-1.zoneA.rds-mysql0....rds-mysql.store.P50":8703,"lamp.us-east-1.zoneA.rds-mysql0....rds-mysql.store.P75":11263,"lamp.us-east-1.zoneA.rds-mysql0....rds-mysql.store.P90":14847,"lamp.us-east-1.zoneA.rds-mysql0....rds-mysql.store.P95":28671,"lamp.us-east-1.zoneA.rds-mysql0....rds-mysql.store.P99":47103,"lamp.us-east-1.zoneA.rds-mysql0....rds-mysql.store.P999":8774143,"lamp.us-east-1.zoneA.webserver0....webserver.monolith.P50":9215,"lamp.us-east-1.zoneA.webserver0....webserver.monolith.P75":13311,"lamp.us-east-1.zoneA.webserver0....webserver.monolith.P90":16895,"lamp.us-east-1.zoneA.webserver0....webserver.monolith.P95":39935,"lamp.us-east-1.zoneA.webserver0....webserver.monolith.P99":159743,"lamp.us-east-1.zoneA.webserver0....webserver.monolith.P999":1124351,"lamp.us-east-1.zoneA.webserver12....webserver.monolith.P50":9215,"lamp.us-east-1.zoneA.webserver12....webserver.monolith.P75":12287,"lamp.us-east-1.zoneA.webserver12....webserver.monolith.P90":17407,"lamp.us-east-1.zoneA.webserver12....webserver.monolith.P95":99327,"lamp.us-east-1.zoneA.webserver12....webserver.monolith.P99":133119,"lamp.us-east-1.zoneA.webserver12....webserver.monolith.P999":972799,"lamp.us-east-1.zoneA.webserver15....webserver.monolith.P50":10751,"lamp.us-east-1.zoneA.webserver15....webserver.monolith.P75":16383,"lamp.us-east-1.zoneA.webserver15....webserver.monolith.P90":33279,"lamp.us-east-1.zoneA.webserver15....webserver.monolith.P95":40959,"lamp.us-east-1.zoneA.webserver15....webserver.monolith.P99":1129983,"lamp.us-east-1.zoneA.webserver15....webserver.monolith.P999":1129983,"lamp.us-east-1.zoneA.webserver3....webserver.monolith.P50":8703,"lamp.us-east-1.zoneA.webserver3....webserver.monolith.P75":12287,"lamp.us-east-1.zoneA.webserver3....webserver.monolith.P90":28671,"lamp.us-east-1.zoneA.webserver3....webserver.monolith.P95":35327,"lamp.us-east-1.zoneA.webserver3....webserver.monolith.P99":72703,"lamp.us-east-1.zoneA.webserver3....webserver.monolith.P999":1019903,"lamp.us-east-1.zoneA.webserver6....webserver.monolith.P50":9215,"lamp.us-east-1.zoneA.webserver6....webserver.monolith.P75":12287,"lamp.us-east-1.zoneA.webserver6....webserver.monolith.P90":16895,"lamp.us-east-1.zoneA.webserver6....webserver.monolith.P95":28159,"lamp.us-east-1.zoneA.webserver6....webserver.monolith.P99":129023,"lamp.us-east-1.zoneA.webserver6....webserver.monolith.P999":1023999,"lamp.us-east-1.zoneA.webserver9....webserver.monolith.P50":9215,"lamp.us-east-1.zoneA.webserver9....webserver.monolith.P75":11263,"lamp.us-east-1.zoneA.webserver9....webserver.monolith.P90":24575,"lamp.us-east-1.zoneA.webserver9....webserver.monolith.P95":33791,"lamp.us-east-1.zoneA.webserver9....webserver.monolith.P99":61439,"lamp.us-east-1.zoneA.webserver9....webserver.monolith.P999":1106431,"lamp.us-east-1.zoneB.eureka1....eureka.eureka.P50":18431,"lamp.us-east-1.zoneB.eureka1....eureka.eureka.P75":52735,"lamp.us-east-1.zoneB.eureka1....eureka.eureka.P90":80895,"lamp.us-east-1.zoneB.eureka1....eureka.eureka.P95":117247,"lamp.us-east-1.zoneB.eureka1....eureka.eureka.P99":6462975,"lamp.us-east-1.zoneB.eureka1....eureka.eureka.P999":6465535,"lamp.us-east-1.zoneB.rds-mysql1....rds-mysql.store.P50":8703,"lamp.us-east-1.zoneB.rds-mysql1....rds-mysql.store.P75":11263,"lamp.us-east-1.zoneB.rds-mysql1....rds-mysql.store.P90":13823,"lamp.us-east-1.zoneB.rds-mysql1....rds-mysql.store.P95":20479,"lamp.us-east-1.zoneB.rds-mysql1....rds-mysql.store.P99":68095,"lamp.us-east-1.zoneB.rds-mysql1....rds-mysql.store.P999":1336319,"lamp.us-east-1.zoneB.webserver1....webserver.monolith.P50":9727,"lamp.us-east-1.zoneB.webserver1....webserver.monolith.P75":13823,"lamp.us-east-1.zoneB.webserver1....webserver.monolith.P90":31231,"lamp.us-east-1.zoneB.webserver1....webserver.monolith.P95":44543,"lamp.us-east-1.zoneB.webserver1....webserver.monolith.P99":197631,"lamp.us-east-1.zoneB.webserver1....webserver.monolith.P999":1138687,"lamp.us-east-1.zoneB.webserver10....webserver.monolith.P50":10751,"lamp.us-east-1.zoneB.webserver10....webserver.monolith.P75":12799,"lamp.us-east-1.zoneB.webserver10....webserver.monolith.P90":36863,"lamp.us-east-1.zoneB.webserver10....webserver.monolith.P95":64511,"lamp.us-east-1.zoneB.webserver10....webserver.monolith.P99":1082367,"lamp.us-east-1.zoneB.webserver10....webserver.monolith.P999":1082367,"lamp.us-east-1.zoneB.webserver13....webserver.monolith.P50":9215,"lamp.us-east-1.zoneB.webserver13....webserver.monolith.P75":12799,"lamp.us-east-1.zoneB.webserver13....webserver.monolith.P90":30207,"lamp.us-east-1.zoneB.webserver13....webserver.monolith.P95":112127,"lamp.us-east-1.zoneB.webserver13....webserver.monolith.P99":294399,"lamp.us-east-1.zoneB.webserver13....webserver.monolith.P999":294399,"lamp.us-east-1.zoneB.webserver16....webserver.monolith.P50":9727,"lamp.us-east-1.zoneB.webserver16....webserver.monolith.P75":13311,"lamp.us-east-1.zoneB.webserver16....webserver.monolith.P90":29695,"lamp.us-east-1.zoneB.webserver16....webserver.monolith.P95":72191,"lamp.us-east-1.zoneB.webserver16....webserver.monolith.P99":114687,"lamp.us-east-1.zoneB.webserver16....webserver.monolith.P999":1005055,"lamp.us-east-1.zoneB.webserver4....webserver.monolith.P50":9215,"lamp.us-east-1.zoneB.webserver4....webserver.monolith.P75":11775,"lamp.us-east-1.zoneB.webserver4....webserver.monolith.P90":28159,"lamp.us-east-1.zoneB.webserver4....webserver.monolith.P95":123903,"lamp.us-east-1.zoneB.webserver4....webserver.monolith.P99":1596415,"lamp.us-east-1.zoneB.webserver4....webserver.monolith.P999":1596415,"lamp.us-east-1.zoneB.webserver7....webserver.monolith.P50":8703,"lamp.us-east-1.zoneB.webserver7....webserver.monolith.P75":12287,"lamp.us-east-1.zoneB.webserver7....webserver.monolith.P90":18431,"lamp.us-east-1.zoneB.webserver7....webserver.monolith.P95":25087,"lamp.us-east-1.zoneB.webserver7....webserver.monolith.P99":91647,"lamp.us-east-1.zoneB.webserver7....webserver.monolith.P999":1004543,"lamp.us-east-1.zoneC.eureka2....eureka.eureka.P50":14847,"lamp.us-east-1.zoneC.eureka2....eureka.eureka.P75":48639,"lamp.us-east-1.zoneC.eureka2....eureka.eureka.P90":80895,"lamp.us-east-1.zoneC.eureka2....eureka.eureka.P95":102399,"lamp.us-east-1.zoneC.eureka2....eureka.eureka.P99":8442367,"lamp.us-east-1.zoneC.eureka2....eureka.eureka.P999":8444927,"lamp.us-east-1.zoneC.webserver11....webserver.monolith.P50":9215,"lamp.us-east-1.zoneC.webserver11....webserver.monolith.P75":12799,"lamp.us-east-1.zoneC.webserver11....webserver.monolith.P90":16383,"lamp.us-east-1.zoneC.webserver11....webserver.monolith.P95":29695,"lamp.us-east-1.zoneC.webserver11....webserver.monolith.P99":148991,"lamp.us-east-1.zoneC.webserver11....webserver.monolith.P999":1025535,"lamp.us-east-1.zoneC.webserver14....webserver.monolith.P50":9215,"lamp.us-east-1.zoneC.webserver14....webserver.monolith.P75":12287,"lamp.us-east-1.zoneC.webserver14....webserver.monolith.P90":58879,"lamp.us-east-1.zoneC.webserver14....webserver.monolith.P95":464895,"lamp.us-east-1.zoneC.webserver14....webserver.monolith.P99":614911,"lamp.us-east-1.zoneC.webserver14....webserver.monolith.P999":1413631,"lamp.us-east-1.zoneC.webserver17....webserver.monolith.P50":9215,"lamp.us-east-1.zoneC.webserver17....webserver.monolith.P75":11775,"lamp.us-east-1.zoneC.webserver17....webserver.monolith.P90":32255,"lamp.us-east-1.zoneC.webserver17....webserver.monolith.P95":39423,"lamp.us-east-1.zoneC.webserver17....webserver.monolith.P99":1160703,"lamp.us-east-1.zoneC.webserver17....webserver.monolith.P999":1160703,"lamp.us-east-1.zoneC.webserver2....webserver.monolith.P50":9215,"lamp.us-east-1.zoneC.webserver2....webserver.monolith.P75":12799,"lamp.us-east-1.zoneC.webserver2....webserver.monolith.P90":20991,"lamp.us-east-1.zoneC.webserver2....webserver.monolith.P95":32255,"lamp.us-east-1.zoneC.webserver2....webserver.monolith.P99":117759,"lamp.us-east-1.zoneC.webserver2....webserver.monolith.P999":1028095,"lamp.us-east-1.zoneC.webserver5....webserver.monolith.P50":9727,"lamp.us-east-1.zoneC.webserver5....webserver.monolith.P75":13311,"lamp.us-east-1.zoneC.webserver5....webserver.monolith.P90":26111,"lamp.us-east-1.zoneC.webserver5....webserver.monolith.P95":36351,"lamp.us-east-1.zoneC.webserver5....webserver.monolith.P99":1125887,"lamp.us-east-1.zoneC.webserver5....webserver.monolith.P999":1125887,"lamp.us-east-1.zoneC.webserver8....webserver.monolith.P50":9215,"lamp.us-east-1.zoneC.webserver8....webserver.monolith.P75":12287,"lamp.us-east-1.zoneC.webserver8....webserver.monolith.P90":22527,"lamp.us-east-1.zoneC.webserver8....webserver.monolith.P95":35839,"lamp.us-east-1.zoneC.webserver8....webserver.monolith.P99":87039,"lamp.us-east-1.zoneC.webserver8....webserver.monolith.P999":1051647}
}
